{
  "backtest": {
    "actual_nasdaq_return": null,
    "actual_nvda_return": null,
    "actual_soxx_return": null,
    "actual_sp500_return": null,
    "actual_vix_return": null,
    "filled_next_day": false,
    "prediction_correct": null
  },
  "confidence": 75.45,
  "date": "2026-07-21",
  "indicators": {
    "AAPL": {
      "above_200d": true,
      "above_50d": true,
      "close": 327.73999,
      "date": "2026-07-21",
      "distance_from_200d": 19.20557405236176,
      "distance_from_50d": 7.725578247477705,
      "group": "portfolio_mega_cap",
      "name": "Apple",
      "return_1d": 0.35212162469300257,
      "return_20d": 10.346445899247625,
      "return_5d": 4.0907087637700235,
      "return_63d": 20.029300275962658,
      "sma_200": 274.936799395,
      "sma_50": 304.23599978,
      "volume": 40800631,
      "volume_ratio_20d": 0.622062762355153,
      "volume_sma_20": 65589251.55
    },
    "AEM": {
      "above_200d": false,
      "above_50d": false,
      "close": 141.619995,
      "date": "2026-07-21",
      "distance_from_200d": -23.04973706208331,
      "distance_from_50d": -14.135874925947112,
      "group": "portfolio_safe_haven",
      "name": "Agnico Eagle Mines",
      "return_1d": 3.872670643176468,
      "return_20d": -15.12137254583018,
      "return_5d": -1.9320053477735466,
      "return_63d": -34.553354750928214,
      "sma_200": 184.04095008,
      "sma_50": 164.93500036,
      "volume": 2275239,
      "volume_ratio_20d": 0.8667273540646833,
      "volume_sma_20": 2625091.95
    },
    "AENA.MC": {
      "above_200d": true,
      "above_50d": true,
      "close": 26.1,
      "date": "2026-07-21",
      "distance_from_200d": 4.566888649718082,
      "distance_from_50d": 2.000937700482419,
      "group": "portfolio_travel",
      "name": "Aena",
      "return_1d": 0.694444444444442,
      "return_20d": -1.4350453172205402,
      "return_5d": -1.5094339622641506,
      "return_63d": 0.694444444444442,
      "sma_200": 24.960100025,
      "sma_50": 25.58800006,
      "volume": 1535586,
      "volume_ratio_20d": 1.0170052564736325,
      "volume_sma_20": 1509909.6
    },
    "AIR.PA": {
      "above_200d": true,
      "above_50d": true,
      "close": 194.600006,
      "date": "2026-07-21",
      "distance_from_200d": 2.4725888768893034,
      "distance_from_50d": 5.107833219837743,
      "group": "portfolio_travel_industrial",
      "name": "Airbus",
      "return_1d": 1.470438530975282,
      "return_20d": 0.6933721590958397,
      "return_5d": -0.6838807728500429,
      "return_63d": 17.059672850707642,
      "sma_200": 189.9044497,
      "sma_50": 185.14320012,
      "volume": 870715,
      "volume_ratio_20d": 0.8572516485466626,
      "volume_sma_20": 1015705.25
    },
    "AMD": {
      "above_200d": true,
      "above_50d": true,
      "close": 544.429993,
      "date": "2026-07-21",
      "distance_from_200d": 81.29705944926945,
      "distance_from_50d": 8.140478105013461,
      "group": "ai_stock",
      "name": "AMD",
      "return_1d": 8.114062678875955,
      "return_20d": -1.3052248671643674,
      "return_5d": -0.6750245318170478,
      "return_63d": 98.010536184301,
      "sma_200": 300.297199885,
      "sma_50": 503.44700018,
      "volume": 27221951,
      "volume_ratio_20d": 0.9598842774239034,
      "volume_sma_20": 28359617.55
    },
    "AMZN": {
      "above_200d": true,
      "above_50d": false,
      "close": 247.550003,
      "date": "2026-07-21",
      "distance_from_200d": 5.632962678597475,
      "distance_from_50d": -1.437565134355212,
      "group": "hyperscaler",
      "name": "Amazon",
      "return_1d": -0.9760398220720834,
      "return_20d": 6.340483029268351,
      "return_5d": 0.02424259517066485,
      "return_63d": -0.2940212674964582,
      "sma_200": 234.349200025,
      "sma_50": 251.16060022,
      "volume": 25711227,
      "volume_ratio_20d": 0.4511587988471806,
      "volume_sma_20": 56989306.35
    },
    "ASML": {
      "above_200d": true,
      "above_50d": true,
      "close": 1801.51001,
      "date": "2026-07-21",
      "distance_from_200d": 31.98736612022437,
      "distance_from_50d": 4.250130058765156,
      "group": "ai_stock",
      "name": "ASML",
      "return_1d": 3.5934025647387235,
      "return_20d": -6.621225346637294,
      "return_5d": 1.4569391758159966,
      "return_63d": 22.012191669488644,
      "sma_200": 1364.910947885,
      "sma_50": 1728.065,
      "volume": 1656760,
      "volume_ratio_20d": 0.7623989456478523,
      "volume_sma_20": 2173088
    },
    "AVGO": {
      "above_200d": true,
      "above_50d": false,
      "close": 386.5,
      "date": "2026-07-21",
      "distance_from_200d": 6.142535825857998,
      "distance_from_50d": -3.7306192561258222,
      "group": "ai_stock",
      "name": "Broadcom",
      "return_1d": 2.205414615978274,
      "return_20d": -1.4357496055421692,
      "return_5d": -0.6707576522355208,
      "return_63d": -3.285540333739456,
      "sma_200": 364.13300002,
      "sma_50": 401.47760068,
      "volume": 16450311,
      "volume_ratio_20d": 0.6815097922271076,
      "volume_sma_20": 24138040.55
    },
    "BABA": {
      "above_200d": false,
      "above_50d": true,
      "close": 117.970001,
      "date": "2026-07-21",
      "distance_from_200d": -17.82558490044187,
      "distance_from_50d": 0.35268561029901946,
      "group": "portfolio_global_consumer",
      "name": "Alibaba",
      "return_1d": -1.9694158872998524,
      "return_20d": 12.38449068891596,
      "return_5d": 5.030271545584042,
      "return_63d": -15.837909193663535,
      "sma_200": 143.56049977,
      "sma_50": 117.55540002,
      "volume": 8436224,
      "volume_ratio_20d": 0.5773556978950044,
      "volume_sma_20": 14611831.2
    },
    "BARC.L": {
      "above_200d": true,
      "above_50d": true,
      "close": 522.400024,
      "date": "2026-07-21",
      "distance_from_200d": 17.316908943120968,
      "distance_from_50d": 8.439567047054153,
      "group": "portfolio_uk_financial",
      "name": "Barclays",
      "return_1d": 1.9516002208461947,
      "return_20d": 2.1309919843597314,
      "return_5d": 0.4808616819759859,
      "return_63d": 19.310269919238053,
      "sma_200": 445.28962509,
      "sma_50": 481.74300048,
      "volume": 48648953,
      "volume_ratio_20d": 1.328902795341768,
      "volume_sma_20": 36608360.8
    },
    "BP.L": {
      "above_200d": true,
      "above_50d": true,
      "close": 529.299988,
      "date": "2026-07-21",
      "distance_from_200d": 8.078801564224047,
      "distance_from_50d": 2.6740231543556536,
      "group": "portfolio_energy",
      "name": "BP",
      "return_1d": 1.4178891856115206,
      "return_20d": 6.146594679393491,
      "return_5d": 2.478216456921589,
      "return_63d": -6.052544293111362,
      "sma_200": 489.73524904,
      "sma_50": 515.5149976,
      "volume": 29164466,
      "volume_ratio_20d": 0.739289436584112,
      "volume_sma_20": 39449320.6
    },
    "BZ=F": {
      "above_200d": true,
      "above_50d": true,
      "close": 91.400002,
      "date": "2026-07-21",
      "distance_from_200d": 14.875210834969321,
      "distance_from_50d": 2.6781723941685875,
      "group": "event_risk",
      "name": "Brent Crude Oil Futures",
      "return_1d": 2.443399434617799,
      "return_20d": 17.32990969627959,
      "return_5d": 7.872062744999564,
      "return_63d": -4.273147121706722,
      "sma_200": 79.5646,
      "sma_50": 89.01600006,
      "volume": 41691,
      "volume_ratio_20d": 0.9809658599598353,
      "volume_sma_20": 42499.95
    },
    "CL=F": {
      "above_200d": true,
      "above_50d": false,
      "close": 84.599998,
      "date": "2026-07-21",
      "distance_from_200d": 13.080361378340477,
      "distance_from_50d": -0.3995811375159808,
      "group": "event_risk",
      "name": "WTI Crude Oil Futures",
      "return_1d": 1.6460350241727095,
      "return_20d": 13.071368618016589,
      "return_5d": 6.629697838653792,
      "return_63d": -5.5908971589008205,
      "sma_200": 74.81404991,
      "sma_50": 84.93939982,
      "volume": 270851,
      "volume_ratio_20d": 1.1446220500259476,
      "volume_sma_20": 236629.2
    },
    "CRCL": {
      "above_200d": false,
      "above_50d": false,
      "close": 71.080002,
      "date": "2026-07-21",
      "distance_from_200d": -23.541814490459966,
      "distance_from_50d": -17.884305218455953,
      "group": "portfolio_fintech",
      "name": "Circle Internet Group",
      "return_1d": 8.601994282749924,
      "return_20d": -11.094428183655847,
      "return_5d": 12.43277582358784,
      "return_63d": -33.17036354672468,
      "sma_200": 92.96584993,
      "sma_50": 86.5607996,
      "volume": 16468960,
      "volume_ratio_20d": 1.0911767915428525,
      "volume_sma_20": 15092843
    },
    "DBK.DE": {
      "above_200d": true,
      "above_50d": true,
      "close": 31.07,
      "date": "2026-07-21",
      "distance_from_200d": 4.306459973260868,
      "distance_from_50d": 5.592278112760685,
      "group": "portfolio_eu_financial",
      "name": "Deutsche Bank",
      "return_1d": 1.3372472276581782,
      "return_20d": 0.3553003990730108,
      "return_5d": -1.1925584353633334,
      "return_63d": 11.62206256950109,
      "sma_200": 29.787225075,
      "sma_50": 29.42450012,
      "volume": 2102797,
      "volume_ratio_20d": 0.48759684763597044,
      "volume_sma_20": 4312573
    },
    "DX-Y.NYB": {
      "above_200d": true,
      "above_50d": true,
      "close": 101.174004,
      "date": "2026-07-21",
      "distance_from_200d": 2.1506456993158007,
      "distance_from_50d": 1.1203290462053372,
      "group": "liquidity",
      "name": "US Dollar Index",
      "return_1d": 0.1822022018457714,
      "return_20d": 0.1524519942323721,
      "return_5d": 0.23182286047507272,
      "return_63d": 3.1861304481551,
      "sma_200": 99.04392019,
      "sma_50": 100.05308028,
      "volume": 0,
      "volume_ratio_20d": null,
      "volume_sma_20": 0
    },
    "EZJ.L": {
      "above_200d": true,
      "above_50d": true,
      "close": 663.400024,
      "date": "2026-07-21",
      "distance_from_200d": 43.115098897772654,
      "distance_from_50d": 31.23173097601015,
      "group": "portfolio_travel",
      "name": "easyJet",
      "return_1d": 0.18121594355997583,
      "return_20d": 25.26436066152693,
      "return_5d": -2.4411729411764616,
      "return_63d": 76.71817650588454,
      "sma_200": 463.54300078,
      "sma_50": 505.51800168,
      "volume": 6209870,
      "volume_ratio_20d": 0.654666994948801,
      "volume_sma_20": 9485540.05
    },
    "GC=F": {
      "above_200d": false,
      "above_50d": false,
      "close": 4088.800049,
      "date": "2026-07-21",
      "distance_from_200d": -8.638373527396936,
      "distance_from_50d": -4.741091211338954,
      "group": "safe_haven",
      "name": "Gold Futures",
      "return_1d": 1.9574595177628717,
      "return_20d": -2.2262573275719677,
      "return_5d": 0.6820799864953209,
      "return_63d": -14.933633636354992,
      "sma_200": 4475.401989725,
      "sma_50": 4292.30200198,
      "volume": 115649,
      "volume_ratio_20d": 17.99998443567654,
      "volume_sma_20": 6424.95
    },
    "GFS": {
      "above_200d": true,
      "above_50d": false,
      "close": 59.389999,
      "date": "2026-07-21",
      "distance_from_200d": 16.75494203628216,
      "distance_from_50d": -21.252639459020795,
      "group": "portfolio_chip",
      "name": "GlobalFoundries",
      "return_1d": 4.541450368923594,
      "return_20d": -33.76826104088906,
      "return_5d": -6.310143655310673,
      "return_63d": 1.0721596688958446,
      "sma_200": 50.867224945,
      "sma_50": 75.41839954,
      "volume": 5321921,
      "volume_ratio_20d": 1.5739525965583014,
      "volume_sma_20": 3381246.05
    },
    "GOOGL": {
      "above_200d": true,
      "above_50d": false,
      "close": 347.149994,
      "date": "2026-07-21",
      "distance_from_200d": 7.572794590762966,
      "distance_from_50d": -5.831887456152607,
      "group": "hyperscaler",
      "name": "Alphabet",
      "return_1d": -1.375037966278525,
      "return_20d": -0.7235183741267193,
      "return_5d": -3.4380172056961755,
      "return_63d": 2.8836407519194918,
      "sma_200": 322.71169985,
      "sma_50": 368.64920048,
      "volume": 22327729,
      "volume_ratio_20d": 0.6797657329213839,
      "volume_sma_20": 32846211.45
    },
    "HYG": {
      "above_200d": false,
      "above_50d": false,
      "close": 79.650002,
      "date": "2026-07-21",
      "distance_from_200d": -0.8057563218440089,
      "distance_from_50d": -0.20822674918632433,
      "group": "credit",
      "name": "High Yield Corporate Bond ETF",
      "return_1d": -0.03764809236949107,
      "return_20d": -0.3627720699831971,
      "return_5d": -0.03764809236949107,
      "return_63d": -1.1541325104459488,
      "sma_200": 80.297000155,
      "sma_50": 79.81620068,
      "volume": 26209745,
      "volume_ratio_20d": 0.8819688934015222,
      "volume_sma_20": 29717312.25
    },
    "IAG.L": {
      "above_200d": true,
      "above_50d": true,
      "close": 442.0,
      "date": "2026-07-21",
      "distance_from_200d": 8.07549115881747,
      "distance_from_50d": 0.886062824713818,
      "group": "portfolio_travel",
      "name": "International Consolidated Airlines",
      "return_1d": 0.8902063333913857,
      "return_20d": -5.515175002526929,
      "return_5d": -3.6407263054529904,
      "return_63d": 12.726343595108226,
      "sma_200": 408.973390045,
      "sma_50": 438.11799928,
      "volume": 10820960,
      "volume_ratio_20d": 0.7314723679613392,
      "volume_sma_20": 14793395.45
    },
    "ISP.MI": {
      "above_200d": true,
      "above_50d": true,
      "close": 6.367,
      "date": "2026-07-21",
      "distance_from_200d": 11.173194112203388,
      "distance_from_50d": 7.111013912487585,
      "group": "portfolio_eu_financial",
      "name": "Intesa Sanpaolo",
      "return_1d": 0.4100299637281202,
      "return_20d": 3.8492904909476433,
      "return_5d": 0.33091711314212624,
      "return_63d": 11.175135323904307,
      "sma_200": 5.7271,
      "sma_50": 5.9443,
      "volume": 41547581,
      "volume_ratio_20d": 0.8403598587139133,
      "volume_sma_20": 49440225.6
    },
    "IWM": {
      "above_200d": true,
      "above_50d": true,
      "close": 296.540009,
      "date": "2026-07-21",
      "distance_from_200d": 12.34501698033581,
      "distance_from_50d": 2.011964655545029,
      "group": "breadth",
      "name": "Russell 2000 ETF",
      "return_1d": 1.4470976117621603,
      "return_20d": -0.5499980007042327,
      "return_5d": 0.6892801368618917,
      "return_63d": 6.919056277215296,
      "sma_200": 263.95475026,
      "sma_50": 290.69140076,
      "volume": 16080233,
      "volume_ratio_20d": 0.7118023955933537,
      "volume_sma_20": 22590866.65
    },
    "JNK": {
      "above_200d": false,
      "above_50d": false,
      "close": 95.900002,
      "date": "2026-07-21",
      "distance_from_200d": -0.8540592336270025,
      "distance_from_50d": -0.24050289524150115,
      "group": "credit",
      "name": "High Yield Bond ETF",
      "return_1d": -0.05210526478702793,
      "return_20d": -0.4153696651494454,
      "return_5d": 0.0,
      "return_63d": -1.1238230977177688,
      "sma_200": 96.72610019,
      "sma_50": 96.13120032,
      "volume": 2013701,
      "volume_ratio_20d": 0.8685773129504244,
      "volume_sma_20": 2318390.05
    },
    "LULU": {
      "above_200d": false,
      "above_50d": false,
      "close": 116.629997,
      "date": "2026-07-21",
      "distance_from_200d": -27.720402306089476,
      "distance_from_50d": -2.5636075584174023,
      "group": "portfolio_consumer",
      "name": "Lululemon",
      "return_1d": -0.03428559242797391,
      "return_20d": 10.623159442283981,
      "return_5d": -0.5881375724514082,
      "return_63d": -30.08213032890271,
      "sma_200": 161.35949939,
      "sma_50": 119.69859934,
      "volume": 1936654,
      "volume_ratio_20d": 0.6502717207816594,
      "volume_sma_20": 2978222.7
    },
    "META": {
      "above_200d": true,
      "above_50d": true,
      "close": 643.809998,
      "date": "2026-07-21",
      "distance_from_200d": 0.6432359143143662,
      "distance_from_50d": 6.285857713631637,
      "group": "hyperscaler",
      "name": "Meta",
      "return_1d": -0.3158594218171884,
      "return_20d": 14.181081032802956,
      "return_5d": -2.6064959115075004,
      "return_63d": -4.0392863559355785,
      "sma_200": 639.69524842,
      "sma_50": 605.73439576,
      "volume": 8401169,
      "volume_ratio_20d": 0.4279754948535225,
      "volume_sma_20": 19630023.45
    },
    "MKS.L": {
      "above_200d": true,
      "above_50d": true,
      "close": 398.299988,
      "date": "2026-07-21",
      "distance_from_200d": 10.455981272186765,
      "distance_from_50d": 9.794535336522902,
      "group": "portfolio_uk_consumer",
      "name": "Marks and Spencer",
      "return_1d": 4.843378333930692,
      "return_20d": 9.453144975869376,
      "return_5d": 7.474360915147948,
      "return_63d": 13.169477033573717,
      "sma_200": 360.59612473,
      "sma_50": 362.76849916,
      "volume": 10979104,
      "volume_ratio_20d": 1.701992929735037,
      "volume_sma_20": 6450734.2
    },
    "MSFT": {
      "above_200d": false,
      "above_50d": false,
      "close": 397.75,
      "date": "2026-07-21",
      "distance_from_200d": -9.222751416834395,
      "distance_from_50d": -0.7653846203914849,
      "group": "hyperscaler",
      "name": "Microsoft",
      "return_1d": -1.1285413255192167,
      "return_20d": 8.278435327254696,
      "return_5d": 3.330477549978794,
      "return_63d": -4.8604316644987104,
      "sma_200": 438.16044902,
      "sma_50": 400.81779778,
      "volume": 23664484,
      "volume_ratio_20d": 0.5355309725575363,
      "volume_sma_20": 44188824.2
    },
    "MU": {
      "above_200d": true,
      "above_50d": true,
      "close": 970.820007,
      "date": "2026-07-21",
      "distance_from_200d": 97.91659880646168,
      "distance_from_50d": 2.824763620714177,
      "group": "ai_stock",
      "name": "Micron",
      "return_1d": 12.173870811100285,
      "return_20d": -19.858343129908274,
      "return_5d": -1.251117672568547,
      "return_63d": 116.49792133608452,
      "sma_200": 490.51975067,
      "sma_50": 944.15000124,
      "volume": 47631170,
      "volume_ratio_20d": 0.920309253024312,
      "volume_sma_20": 51755613.5
    },
    "NDA-FI.HE": {
      "above_200d": true,
      "above_50d": true,
      "close": 17.254999,
      "date": "2026-07-21",
      "distance_from_200d": 9.413832173303271,
      "distance_from_50d": 5.101897858245663,
      "group": "portfolio_eu_financial",
      "name": "Nordea Bank",
      "return_1d": 0.8769307220111155,
      "return_20d": 4.989352296279415,
      "return_5d": 1.7693836626364146,
      "return_63d": 8.692907086614188,
      "sma_200": 15.77040001,
      "sma_50": 16.41740002,
      "volume": 2739630,
      "volume_ratio_20d": 0.7205504086375047,
      "volume_sma_20": 3802135.1
    },
    "NVDA": {
      "above_200d": true,
      "above_50d": false,
      "close": 207.289993,
      "date": "2026-07-21",
      "distance_from_200d": 7.639078924332265,
      "distance_from_50d": -1.1679278484674094,
      "group": "ai_stock",
      "name": "NVIDIA",
      "return_1d": 1.972645621667879,
      "return_20d": -0.6518097479552232,
      "return_5d": -2.129372018941844,
      "return_63d": 2.5883376481078635,
      "sma_200": 192.578750275,
      "sma_50": 209.7396002,
      "volume": 106460638,
      "volume_ratio_20d": 0.7794349914878279,
      "volume_sma_20": 136586936.9
    },
    "NVTS": {
      "above_200d": true,
      "above_50d": false,
      "close": 12.825,
      "date": "2026-07-21",
      "distance_from_200d": 0.9407361389712987,
      "distance_from_50d": -37.220982265779725,
      "group": "portfolio_ai_chip",
      "name": "Navitas Semiconductor",
      "return_1d": 11.135181975736575,
      "return_20d": -45.886078232654924,
      "return_5d": -2.024446142093206,
      "return_63d": -2.840909090909094,
      "sma_200": 12.705475005,
      "sma_50": 20.42880004,
      "volume": 11618093,
      "volume_ratio_20d": 0.677047822279388,
      "volume_sma_20": 17159929.65
    },
    "NWG.L": {
      "above_200d": true,
      "above_50d": true,
      "close": 679.0,
      "date": "2026-07-21",
      "distance_from_200d": 11.63113097495605,
      "distance_from_50d": 8.545521519573086,
      "group": "portfolio_financial",
      "name": "NatWest Group",
      "return_1d": 2.0438796978462292,
      "return_20d": 3.3171009741247426,
      "return_5d": 4.493692295974627,
      "return_63d": 12.865695991982552,
      "sma_200": 608.253265975,
      "sma_50": 625.54400264,
      "volume": 17930064,
      "volume_ratio_20d": 0.7966439080354623,
      "volume_sma_20": 22506999.45
    },
    "ORCL": {
      "above_200d": false,
      "above_50d": false,
      "close": 127.050003,
      "date": "2026-07-21",
      "distance_from_200d": -33.10642175138242,
      "distance_from_50d": -27.755606040451152,
      "group": "hyperscaler",
      "name": "Oracle",
      "return_1d": 4.671285335424757,
      "return_20d": -27.429029576722407,
      "return_5d": -0.695637788093828,
      "return_63d": -28.4547800602007,
      "sma_200": 189.928549685,
      "sma_50": 175.8614005,
      "volume": 24504133,
      "volume_ratio_20d": 0.6104596706849285,
      "volume_sma_20": 40140461.65
    },
    "PLTR": {
      "above_200d": false,
      "above_50d": true,
      "close": 132.660004,
      "date": "2026-07-21",
      "distance_from_200d": -14.488619557467741,
      "distance_from_50d": 0.18828117424858348,
      "group": "portfolio_ai_software",
      "name": "Palantir",
      "return_1d": -1.62402810719936,
      "return_20d": 11.01255564853556,
      "return_5d": -0.7926989171949006,
      "return_63d": -9.068472884148838,
      "sma_200": 155.137249935,
      "sma_50": 132.41069958,
      "volume": 22019189,
      "volume_ratio_20d": 0.5224802754622211,
      "volume_sma_20": 42143579.45
    },
    "QQQ": {
      "above_200d": true,
      "above_50d": false,
      "close": 708.969971,
      "date": "2026-07-21",
      "distance_from_200d": 10.457560064747229,
      "distance_from_50d": -1.4349716413309177,
      "group": "major_etf",
      "name": "Invesco QQQ ETF",
      "return_1d": 1.8547212937238822,
      "return_20d": -3.9271008237343863,
      "return_5d": -1.4895345176686337,
      "return_63d": 9.613629634811694,
      "sma_200": 641.84829955,
      "sma_50": 719.2916015,
      "volume": 29987617,
      "volume_ratio_20d": 0.7481932743589007,
      "volume_sma_20": 40080040.85
    },
    "RSP": {
      "above_200d": true,
      "above_50d": true,
      "close": 212.759995,
      "date": "2026-07-21",
      "distance_from_200d": 7.109547229514002,
      "distance_from_50d": 1.5391196362620985,
      "group": "breadth",
      "name": "S&P 500 Equal Weight ETF",
      "return_1d": 0.160058847190081,
      "return_20d": 1.502788027752544,
      "return_5d": -0.323261658326468,
      "return_63d": 4.396463134497597,
      "sma_200": 198.637750325,
      "sma_50": 209.53500066,
      "volume": 6357462,
      "volume_ratio_20d": 0.6662293158139808,
      "volume_sma_20": 9542453.1
    },
    "RYA.IR": {
      "above_200d": false,
      "above_50d": false,
      "close": 25.049999,
      "date": "2026-07-21",
      "distance_from_200d": -4.922946139379913,
      "distance_from_50d": -1.2387575430853448,
      "group": "portfolio_travel",
      "name": "Ryanair",
      "return_1d": 1.0895802627288065,
      "return_20d": -4.49866946244758,
      "return_5d": -5.005695676689581,
      "return_63d": 2.7903076409393712,
      "sma_200": 26.347050085,
      "sma_50": 25.36419994,
      "volume": 2049695,
      "volume_ratio_20d": 0.8748068976538947,
      "volume_sma_20": 2343025.65
    },
    "SGLN.L": {
      "above_200d": false,
      "above_50d": false,
      "close": 5913.0,
      "date": "2026-07-21",
      "distance_from_200d": -8.904847701014408,
      "distance_from_50d": -4.5230836799545315,
      "group": "portfolio_safe_haven",
      "name": "iShares Physical Gold ETC",
      "return_1d": 1.9307016031718582,
      "return_20d": -2.714708785784803,
      "return_5d": -0.0169090294217078,
      "return_63d": -13.235509904622155,
      "sma_200": 6491.015,
      "sma_50": 6193.12,
      "volume": 283573,
      "volume_ratio_20d": 0.7814923018710475,
      "volume_sma_20": 362860.9
    },
    "SHEL.L": {
      "above_200d": true,
      "above_50d": true,
      "close": 3254.0,
      "date": "2026-07-21",
      "distance_from_200d": 8.586926687973605,
      "distance_from_50d": 4.6002912349842,
      "group": "portfolio_energy",
      "name": "Shell",
      "return_1d": 1.0559006211180222,
      "return_20d": 8.30421035113995,
      "return_5d": 3.4000635525897716,
      "return_63d": -0.6715506715506692,
      "sma_200": 2996.6775,
      "sma_50": 3110.89,
      "volume": 7221686,
      "volume_ratio_20d": 0.78716449272054,
      "volume_sma_20": 9174303.55
    },
    "SI=F": {
      "above_200d": false,
      "above_50d": false,
      "close": 59.025002,
      "date": "2026-07-21",
      "distance_from_200d": -15.038804622688062,
      "distance_from_50d": -13.237161018602816,
      "group": "safe_haven",
      "name": "Silver Futures",
      "return_1d": 3.913601771543318,
      "return_20d": -9.922624261754699,
      "return_5d": 0.4304822097339178,
      "return_63d": -26.17352509279559,
      "sma_200": 69.472894935,
      "sma_50": 68.03027966,
      "volume": 35314,
      "volume_ratio_20d": 9.84760390959412,
      "volume_sma_20": 3586.05
    },
    "SMCI": {
      "above_200d": false,
      "above_50d": false,
      "close": 25.5,
      "date": "2026-07-21",
      "distance_from_200d": -24.574845920618984,
      "distance_from_50d": -22.56912551590847,
      "group": "portfolio_ai_infra",
      "name": "Super Micro Computer",
      "return_1d": 7.007973143096935,
      "return_20d": -28.087984435645364,
      "return_5d": -7.775768535262206,
      "return_63d": -11.489063224195185,
      "sma_200": 33.808349895,
      "sma_50": 32.93259978,
      "volume": 26859226,
      "volume_ratio_20d": 0.6664899515816334,
      "volume_sma_20": 40299521.3
    },
    "SMH": {
      "above_200d": true,
      "above_50d": false,
      "close": 584.080017,
      "date": "2026-07-21",
      "distance_from_200d": 32.104003374773725,
      "distance_from_50d": -2.3922625692903154,
      "group": "ai_etf",
      "name": "VanEck Semiconductor ETF",
      "return_1d": 4.518368597225875,
      "return_20d": -12.681819590691024,
      "return_5d": -2.703599982354443,
      "return_63d": 25.890169051236136,
      "sma_200": 442.13650008999997,
      "sma_50": 598.39520142,
      "volume": 6910854,
      "volume_ratio_20d": 0.5795465783693301,
      "volume_sma_20": 11924587.7
    },
    "SOXX": {
      "above_200d": true,
      "above_50d": false,
      "close": 552.690002,
      "date": "2026-07-21",
      "distance_from_200d": 40.40852336798524,
      "distance_from_50d": -2.682127153299918,
      "group": "ai_etf",
      "name": "iShares Semiconductor ETF",
      "return_1d": 5.447015336159766,
      "return_20d": -15.621136538050761,
      "return_5d": -2.681712469342701,
      "return_63d": 32.36499051222583,
      "sma_200": 393.62995119,
      "sma_50": 567.92240298,
      "volume": 9664242,
      "volume_ratio_20d": 0.9443147602130326,
      "volume_sma_20": 10234132.1
    },
    "SPY": {
      "above_200d": true,
      "above_50d": true,
      "close": 748.280029,
      "date": "2026-07-21",
      "distance_from_200d": 7.284859105353814,
      "distance_from_50d": 0.45650691876977234,
      "group": "major_etf",
      "name": "SPDR S&P 500 ETF",
      "return_1d": 0.8341308702158434,
      "return_20d": 0.5225774018476237,
      "return_5d": -0.4721796043958726,
      "return_63d": 5.581902531147942,
      "sma_200": 697.47030032,
      "sma_50": 744.87960208,
      "volume": 27416531,
      "volume_ratio_20d": 0.5487910935941109,
      "volume_sma_20": 49958046.55
    },
    "STM": {
      "above_200d": null,
      "above_50d": null,
      "close": 65.43,
      "date": "2026-07-21",
      "distance_from_200d": null,
      "distance_from_50d": null,
      "group": "portfolio_chip",
      "name": "STMicroelectronics",
      "return_1d": null,
      "return_20d": null,
      "return_5d": null,
      "return_63d": null,
      "sma_200": null,
      "sma_50": null,
      "volume": 9613940,
      "volume_ratio_20d": null,
      "volume_sma_20": null
    },
    "STMPA.PA": {
      "above_200d": true,
      "above_50d": false,
      "close": 57.25,
      "date": "2026-07-21",
      "distance_from_200d": 60.75655854172304,
      "distance_from_50d": -6.352644045173195,
      "group": "portfolio_chip",
      "name": "STMicroelectronics Paris",
      "return_1d": 4.261518849025681,
      "return_20d": -9.799906888295151,
      "return_5d": -6.698176227213548,
      "return_63d": 52.82968907714065,
      "sma_200": 35.61285494,
      "sma_50": 61.1336,
      "volume": 2271622,
      "volume_ratio_20d": 0.8908677391683272,
      "volume_sma_20": 2549898.15
    },
    "SWKS": {
      "above_200d": false,
      "above_50d": false,
      "close": 62.950001,
      "date": "2026-07-21",
      "distance_from_200d": -3.2170512215513702,
      "distance_from_50d": -9.529378878595473,
      "group": "portfolio_chip",
      "name": "Skyworks Solutions",
      "return_1d": 5.267561960996026,
      "return_20d": -17.36676161722237,
      "return_5d": 11.258393027274893,
      "return_63d": 5.869495557845528,
      "sma_200": 65.04244993,
      "sma_50": 69.5806,
      "volume": 5475167,
      "volume_ratio_20d": 1.0003889338725354,
      "volume_sma_20": 5473038.35
    },
    "TLT": {
      "above_200d": false,
      "above_50d": false,
      "close": 83.660004,
      "date": "2026-07-21",
      "distance_from_200d": -4.403042973241023,
      "distance_from_50d": -1.8264041689060817,
      "group": "safe_haven",
      "name": "20+ Year Treasury Bond ETF",
      "return_1d": -0.27416259714104774,
      "return_20d": -2.8226183214133282,
      "return_5d": -0.49952187203800014,
      "return_63d": -3.8943123298915916,
      "sma_200": 87.513250005,
      "sma_50": 85.21639988,
      "volume": 14110749,
      "volume_ratio_20d": 0.6219252735889063,
      "volume_sma_20": 22688817.45
    },
    "TSLA": {
      "above_200d": false,
      "above_50d": false,
      "close": 378.929993,
      "date": "2026-07-21",
      "distance_from_200d": -8.970097503176788,
      "distance_from_50d": -7.252165856908299,
      "group": "portfolio_consumer_ai",
      "name": "Tesla",
      "return_1d": 2.532669270425947,
      "return_20d": -6.448585550877728,
      "return_5d": -4.354081555047129,
      "return_63d": -3.457326624203816,
      "sma_200": 416.26979993,
      "sma_50": 408.55939818,
      "volume": 31140392,
      "volume_ratio_20d": 0.7810787759047384,
      "volume_sma_20": 39868439.6
    },
    "TSM": {
      "above_200d": true,
      "above_50d": false,
      "close": 424.609985,
      "date": "2026-07-21",
      "distance_from_200d": 20.272247679731727,
      "distance_from_50d": -0.21770525383546513,
      "group": "ai_stock",
      "name": "Taiwan Semiconductor",
      "return_1d": 5.545612146525847,
      "return_20d": -9.207352792149193,
      "return_5d": 1.0038226050635313,
      "return_63d": 15.937635592443101,
      "sma_200": 353.040699905,
      "sma_50": 425.5364001,
      "volume": 18100805,
      "volume_ratio_20d": 1.1626672397954432,
      "volume_sma_20": 15568345.25
    },
    "TTE.PA": {
      "above_200d": true,
      "above_50d": false,
      "close": 72.809998,
      "date": "2026-07-21",
      "distance_from_200d": 10.851905578409005,
      "distance_from_50d": -0.780295772166717,
      "group": "portfolio_energy",
      "name": "TotalEnergies",
      "return_1d": 2.3474824620112633,
      "return_20d": 2.824459901834775,
      "return_5d": 2.261237454827425,
      "return_63d": -4.222571858296719,
      "sma_200": 65.682224965,
      "sma_50": 73.38259932,
      "volume": 3925821,
      "volume_ratio_20d": 1.1112505977561,
      "volume_sma_20": 3532795.4
    },
    "UBER": {
      "above_200d": false,
      "above_50d": false,
      "close": 71.550003,
      "date": "2026-07-21",
      "distance_from_200d": -10.186458278545206,
      "distance_from_50d": -1.6232465303104182,
      "group": "portfolio_consumer_platform",
      "name": "Uber",
      "return_1d": -0.8590758170729074,
      "return_20d": 0.1680008399832067,
      "return_5d": -0.7352927098975282,
      "return_63d": -7.665498971880213,
      "sma_200": 79.66505009,
      "sma_50": 72.73059994,
      "volume": 9961200,
      "volume_ratio_20d": 0.516840967061065,
      "volume_sma_20": 19273240
    },
    "UCG.MI": {
      "above_200d": true,
      "above_50d": true,
      "close": 82.620003,
      "date": "2026-07-21",
      "distance_from_200d": 18.519670400417844,
      "distance_from_50d": 7.877319741662703,
      "group": "portfolio_eu_financial",
      "name": "UniCredit",
      "return_1d": 1.8742355579342895,
      "return_20d": 4.741387097162275,
      "return_5d": 0.5721253664729087,
      "return_63d": 25.791721985383663,
      "sma_200": 69.70995002,
      "sma_50": 76.58700012,
      "volume": 4556226,
      "volume_ratio_20d": 1.0149689127724941,
      "volume_sma_20": 4489030.1
    },
    "UNH": {
      "above_200d": true,
      "above_50d": true,
      "close": 436.350006,
      "date": "2026-07-21",
      "distance_from_200d": 27.500204733155087,
      "distance_from_50d": 7.661046687995587,
      "group": "portfolio_defensive",
      "name": "UnitedHealth Group",
      "return_1d": 3.5108571750214423,
      "return_20d": 7.295665759490655,
      "return_5d": 2.6247098820540993,
      "return_63d": 34.89241720101215,
      "sma_200": 342.23474928,
      "sma_50": 405.29979916,
      "volume": 5462224,
      "volume_ratio_20d": 0.8708346015876662,
      "volume_sma_20": 6272401.2
    },
    "USO": {
      "above_200d": true,
      "above_50d": true,
      "close": 128.850006,
      "date": "2026-07-21",
      "distance_from_200d": 31.62828422810979,
      "distance_from_50d": 2.6230446931344797,
      "group": "energy",
      "name": "United States Oil Fund",
      "return_1d": 2.6611456830348823,
      "return_20d": 14.340228692160295,
      "return_5d": 7.223107384923155,
      "return_63d": 6.206730959446105,
      "sma_200": 97.889299975,
      "sma_50": 125.55660026,
      "volume": 5839304,
      "volume_ratio_20d": 0.9621644372878413,
      "volume_sma_20": 6068925.2
    },
    "XLE": {
      "above_200d": true,
      "above_50d": true,
      "close": 58.5,
      "date": "2026-07-21",
      "distance_from_200d": 12.467287429539219,
      "distance_from_50d": 3.3689438991667986,
      "group": "energy",
      "name": "Energy Select Sector SPDR Fund",
      "return_1d": 0.9665188292460991,
      "return_20d": 8.213094557656419,
      "return_5d": 2.7216838854840386,
      "return_63d": 6.228436535318682,
      "sma_200": 52.015124875,
      "sma_50": 56.5934001,
      "volume": 20135456,
      "volume_ratio_20d": 0.6613217185601473,
      "volume_sma_20": 30447292.8
    },
    "^GSPC": {
      "above_200d": true,
      "above_50d": true,
      "close": 7509.200195,
      "date": "2026-07-21",
      "distance_from_200d": 7.3510659282162605,
      "distance_from_50d": 0.5263397209377407,
      "group": "major_index",
      "name": "S&P 500",
      "return_1d": 0.885636599780204,
      "return_20d": 0.48723643792984994,
      "return_5d": -0.45587909352405864,
      "return_63d": 5.627404303339878,
      "sma_200": 6994.99360353,
      "sma_50": 7469.88323244,
      "volume": 2805889000,
      "volume_ratio_20d": 0.5274820910536843,
      "volume_sma_20": 5319401450
    },
    "^IXIC": {
      "above_200d": true,
      "above_50d": false,
      "close": 25837.207031,
      "date": "2026-07-21",
      "distance_from_200d": 8.074232206528542,
      "distance_from_50d": -1.135836919593236,
      "group": "major_index",
      "name": "Nasdaq Composite",
      "return_1d": 1.2903238660321614,
      "return_20d": -1.2588283648697907,
      "return_5d": -1.0334493969944014,
      "return_63d": 5.871141910555289,
      "sma_200": 23906.907783185,
      "sma_50": 26134.04718754,
      "volume": 7055691000,
      "volume_ratio_20d": 0.7626888881453115,
      "volume_sma_20": 9251073550
    },
    "^TNX": {
      "above_200d": true,
      "above_50d": true,
      "close": 4.628,
      "date": "2026-07-21",
      "distance_from_200d": 8.715312932377106,
      "distance_from_50d": 2.7718190256663,
      "group": "rates",
      "name": "US 10Y Treasury Yield",
      "return_1d": 0.6524575902566498,
      "return_20d": 2.6391661122199928,
      "return_5d": 0.9378407851690307,
      "return_63d": 8.894117647058831,
      "sma_200": 4.25699,
      "sma_50": 4.50318,
      "volume": 0,
      "volume_ratio_20d": null,
      "volume_sma_20": 0
    },
    "^VIX": {
      "above_200d": false,
      "above_50d": false,
      "close": 16.950001,
      "date": "2026-07-21",
      "distance_from_200d": -9.37645707744994,
      "distance_from_50d": -2.302091476470347,
      "group": "volatility",
      "name": "CBOE Volatility Index",
      "return_1d": -9.115276139410177,
      "return_20d": -1.9097221117058916,
      "return_5d": 2.727278787878795,
      "return_63d": -13.076917948717949,
      "sma_200": 18.7037501,
      "sma_50": 17.34940006,
      "volume": 0,
      "volume_ratio_20d": null,
      "volume_sma_20": 0
    },
    "derived": {
      "available_symbols": [
        "AAPL",
        "AEM",
        "AENA.MC",
        "AIR.PA",
        "AMD",
        "AMZN",
        "ASML",
        "AVGO",
        "BABA",
        "BARC.L",
        "BP.L",
        "BZ=F",
        "CL=F",
        "CRCL",
        "DBK.DE",
        "DX-Y.NYB",
        "EZJ.L",
        "GC=F",
        "GFS",
        "GOOGL",
        "HYG",
        "IAG.L",
        "ISP.MI",
        "IWM",
        "JNK",
        "LULU",
        "META",
        "MKS.L",
        "MSFT",
        "MU",
        "NDA-FI.HE",
        "NVDA",
        "NVTS",
        "NWG.L",
        "ORCL",
        "PLTR",
        "QQQ",
        "RSP",
        "RYA.IR",
        "SGLN.L",
        "SHEL.L",
        "SI=F",
        "SMCI",
        "SMH",
        "SOXX",
        "SPY",
        "STM",
        "STMPA.PA",
        "SWKS",
        "TLT",
        "TSLA",
        "TSM",
        "TTE.PA",
        "UBER",
        "UCG.MI",
        "UNH",
        "USO",
        "XLE",
        "^GSPC",
        "^IXIC",
        "^TNX",
        "^VIX"
      ],
      "unavailable_symbols": []
    }
  },
  "market_health_score": 56.81,
  "metadata": {
    "data_source": "Yahoo Finance chart endpoint",
    "engine_version": "1.0",
    "fetch_errors": {
      "market_data": {},
      "news": {}
    },
    "generated_at": "2026-07-21T20:15:35+00:00"
  },
  "news": {
    "errors": {},
    "groups": {
      "ai": [
        {
          "link": "https://www.fool.com/investing/2026/07/21/why-msci-stock-is-plummeting-lower-today/?.tsrc=rss",
          "published": "Tue, 21 Jul 2026 20:05:53 +0000",
          "source": "Yahoo Finance",
          "title": "Why MSCI Stock Is Plummeting Lower Today"
        },
        {
          "link": "https://247wallst.com/investing/2026/07/21/beyond-gld-the-0-40-fee-drag-that-is-slowly-bleeding-your-gold-returns/?.tsrc=rss",
          "published": "Tue, 21 Jul 2026 19:47:28 +0000",
          "source": "Yahoo Finance",
          "title": "Beyond GLD: The 0.40% Fee Drag That Is Slowly Bleeding Your Gold Returns"
        },
        {
          "link": "https://247wallst.com/investing/2026/07/21/we-must-act-now-16-nobel-laureates-issue-stark-warning-about-ai-job-threats/?.tsrc=rss",
          "published": "Tue, 21 Jul 2026 19:46:25 +0000",
          "source": "Yahoo Finance",
          "title": "\u201cWe Must Act Now\u201d: 16 Nobel Laureates Issue Stark Warning About AI Job Threats"
        },
        {
          "link": "https://www.fool.com/investing/2026/07/21/verizon-is-cutting-3000-jobs-and-handing-274-store/?.tsrc=rss",
          "published": "Tue, 21 Jul 2026 19:46:00 +0000",
          "source": "Yahoo Finance",
          "title": "Verizon Is Cutting 3,000 Jobs and Handing 274 Stores to Franchisees Right Before July 24 Earnings. Is the 6.5% Dividend Still Safe?"
        },
        {
          "link": "https://www.fool.com/investing/2026/07/21/why-lockheed-martin-stock-dropped-tuesday-morning/?.tsrc=rss",
          "published": "Tue, 21 Jul 2026 19:25:49 +0000",
          "source": "Yahoo Finance",
          "title": "Why Lockheed Martin Stock Dropped Tuesday Morning"
        },
        {
          "link": "https://www.fool.com/investing/2026/07/21/prediction-this-artificial-intelligence-ai-chip-st/?.tsrc=rss",
          "published": "Tue, 21 Jul 2026 19:25:00 +0000",
          "source": "Yahoo Finance",
          "title": "Prediction: This Artificial Intelligence (AI) Chip Stock Is the Biggest Winner From the $26.5 Billion SK Hynix IPO (Hint: It's Not Nvidia)"
        }
      ],
      "energy": [
        {
          "link": "https://finance.yahoo.com/energy/articles/sector-energy-stocks-rise-afternoon-195659469.html?.tsrc=rss",
          "published": "Tue, 21 Jul 2026 19:56:59 +0000",
          "source": "Yahoo Finance",
          "title": "Sector Update: Energy Stocks Rise Late Afternoon"
        },
        {
          "link": "https://www.fool.com/coverage/etfs/2026/07/21/is-mlpx-or-xle-the-superior-energy-etf-for-investors-in-2026/?.tsrc=rss",
          "published": "Tue, 21 Jul 2026 19:04:01 +0000",
          "source": "Yahoo Finance",
          "title": "Is MLPX or XLE the Superior Energy ETF For Investors in 2026?"
        },
        {
          "link": "https://finance.yahoo.com/markets/stocks/articles/top-midday-gainers-175504119.html?.tsrc=rss",
          "published": "Tue, 21 Jul 2026 17:55:04 +0000",
          "source": "Yahoo Finance",
          "title": "Top Midday Gainers"
        },
        {
          "link": "https://finance.yahoo.com/markets/stocks/articles/technology-leads-us-equity-indexes-174726261.html?.tsrc=rss",
          "published": "Tue, 21 Jul 2026 17:47:26 +0000",
          "source": "Yahoo Finance",
          "title": "Update: Technology Leads US Equity Indexes Higher While Traders Weigh Escalation in Middle East"
        },
        {
          "link": "https://finance.yahoo.com/energy/articles/sector-energy-stocks-higher-tuesday-174434515.html?.tsrc=rss",
          "published": "Tue, 21 Jul 2026 17:44:34 +0000",
          "source": "Yahoo Finance",
          "title": "Sector Update: Energy Stocks Higher Tuesday Afternoon"
        },
        {
          "link": "https://wwd.com/sourcing-journal/logistics/houthis-saudi-arabia-ports-ocean-carriers-container-market-energy-iran-war-1239077182/?.tsrc=rss",
          "published": "Tue, 21 Jul 2026 17:38:44 +0000",
          "source": "Yahoo Finance",
          "title": "Houthi Warning on Saudi Ports Could Have Carriers Again Rethinking Red Sea"
        }
      ],
      "geopolitical": [
        {
          "link": "https://finance.yahoo.com/markets/stocks/articles/us-equity-indexes-rise-chipmakers-195424609.html?.tsrc=rss",
          "published": "Tue, 21 Jul 2026 19:54:24 +0000",
          "source": "Yahoo Finance",
          "title": "Update: US Equity Indexes Rise as Chipmakers Lift Technology Amid Worsening Iran Geopolitics"
        },
        {
          "link": "https://finance.yahoo.com/video/market-strategist-says-really-good-194558742.html?.tsrc=rss",
          "published": "Tue, 21 Jul 2026 19:45:58 +0000",
          "source": "Yahoo Finance",
          "title": "Market strategist says it's a 'really good time'\u00a0to consider gold"
        },
        {
          "link": "https://finance.yahoo.com/video/market-strategist-sees-potential-several-194222805.html?.tsrc=rss",
          "published": "Tue, 21 Jul 2026 19:42:22 +0000",
          "source": "Yahoo Finance",
          "title": "Market strategist sees potential for several Fed rate hikes in 2027"
        },
        {
          "link": "https://finance.yahoo.com/energy/articles/wti-oil-rises-again-fighting-194035210.html?.tsrc=rss",
          "published": "Tue, 21 Jul 2026 19:40:35 +0000",
          "source": "Yahoo Finance",
          "title": "Update: WTI Oil Rises Again as Fighting Between US and Iran Keeps Tankers Trapped in Persian Gulf"
        },
        {
          "link": "https://finance.yahoo.com/energy/articles/oil-jumps-amid-growing-middle-192051583.html?.tsrc=rss",
          "published": "Tue, 21 Jul 2026 19:20:51 +0000",
          "source": "Yahoo Finance",
          "title": "Oil Jumps Amid Growing Middle East Tensions"
        },
        {
          "link": "https://finance.yahoo.com/m/dc8d6312-9fef-342a-bab6-d7eb2ff69a3e/halliburton-earnings-beat.html?.tsrc=rss",
          "published": "Tue, 21 Jul 2026 18:11:00 +0000",
          "source": "Yahoo Finance",
          "title": "Halliburton Earnings Beat Estimates. Why the Stock Is Falling."
        }
      ],
      "macro": [
        {
          "link": "https://www.thestreet.com/crypto/markets/edtech-stock-surges-150-on-ai-deal?.tsrc=rss",
          "published": "Tue, 21 Jul 2026 19:15:00 +0000",
          "source": "Yahoo Finance",
          "title": "Edtech stock surges 150% on AI deal"
        },
        {
          "link": "https://finance.yahoo.com/markets/commodities/articles/gold-trading-higher-finds-support-174423525.html?.tsrc=rss",
          "published": "Tue, 21 Jul 2026 17:44:23 +0000",
          "source": "Yahoo Finance",
          "title": "Update: Gold Trading Higher, Finds Support at $4,000 Even as Dollar and Yields Rise"
        },
        {
          "link": "https://uk.finance.yahoo.com/news/ftse-100-ends-healey-pledges-162610936.html?.tsrc=rss",
          "published": "Tue, 21 Jul 2026 16:26:10 +0000",
          "source": "Yahoo Finance",
          "title": "FTSE 100 ends up as Healey pledges fiscal control"
        },
        {
          "link": "https://finance.yahoo.com/m/c66a9685-c10a-3109-ba32-460497218d0c/oil-prices-climb-to-highest.html?.tsrc=rss",
          "published": "Tue, 21 Jul 2026 14:49:20 +0000",
          "source": "Yahoo Finance",
          "title": "Oil Prices Climb to Highest Level Seen in Over a Month"
        },
        {
          "link": "https://finance.yahoo.com/economy/policy/articles/treasury-yields-hit-two-month-143119607.html?.tsrc=rss",
          "published": "Tue, 21 Jul 2026 14:31:19 +0000",
          "source": "Yahoo Finance",
          "title": "Treasury Yields Hit Two-Month High as Oil Sparks Inflation Risk"
        },
        {
          "link": "https://www.thestreet.com/crypto/markets/tokenized-u-s-treasuries-surge-2-5-times-in-a-year?.tsrc=rss",
          "published": "Tue, 21 Jul 2026 14:30:00 +0000",
          "source": "Yahoo Finance",
          "title": "Tokenized U.S. Treasuries surge 2.5 times in a year"
        }
      ],
      "market": [
        {
          "link": "https://247wallst.com/investing/etf/2026/07/21/mags-delivered-181-since-launch-but-equal-weighted-tech-concentration-is-now-a-liability/?.tsrc=rss",
          "published": "Tue, 21 Jul 2026 19:34:35 +0000",
          "source": "Yahoo Finance",
          "title": "MAGS Delivered 181% Since Launch, But Equal-Weighted Tech Concentration Is Now a Liability"
        },
        {
          "link": "https://247wallst.com/investing/etf/2026/07/21/vea-is-crushing-spy-this-year-but-the-decade-long-scorecard-tells-a-different-story/?.tsrc=rss",
          "published": "Tue, 21 Jul 2026 18:34:16 +0000",
          "source": "Yahoo Finance",
          "title": "VEA Is Crushing SPY This Year, but the Decade-Long Scorecard Tells a Different Story"
        },
        {
          "link": "https://finance.yahoo.com/markets/stocks/articles/exchange-traded-funds-higher-us-171046850.html?.tsrc=rss",
          "published": "Tue, 21 Jul 2026 17:10:46 +0000",
          "source": "Yahoo Finance",
          "title": "Exchange-Traded Funds Higher as US Equities Advance After Midday"
        },
        {
          "link": "https://247wallst.com/investing/2026/07/21/buy-alphabet-at-350-because-wall-streets-former-fear-is-now-officially-dead/?.tsrc=rss",
          "published": "Tue, 21 Jul 2026 16:47:24 +0000",
          "source": "Yahoo Finance",
          "title": "Buy Alphabet at $350 Because Wall Street\u2019s Former Fear is Now Officially Dead"
        },
        {
          "link": "https://247wallst.com/investing/etf/2026/07/21/industrials-are-up-17-and-still-catching-the-next-wave-of-ai-money/?.tsrc=rss",
          "published": "Tue, 21 Jul 2026 16:02:57 +0000",
          "source": "Yahoo Finance",
          "title": "Industrials Are Up 17% and Still Catching the Next Wave of AI Money"
        },
        {
          "link": "https://finance.yahoo.com/markets/options/articles/4-high-yield-etfs-to-buy-when-the-vix-spikes-in-2026-152952523.html?.tsrc=rss",
          "published": "Tue, 21 Jul 2026 15:29:52 +0000",
          "source": "Yahoo Finance",
          "title": "4 High-Yield ETFs to Buy When the VIX Spikes in 2026"
        }
      ]
    },
    "portfolio_symbols": {
      "AAPL": [
        {
          "link": "https://finance.yahoo.com/markets/stocks/articles/sector-tech-stocks-gain-afternoon-193632667.html?.tsrc=rss",
          "published": "Tue, 21 Jul 2026 19:36:32 +0000",
          "source": "Yahoo Finance",
          "title": "Sector Update: Tech Stocks Gain Late Afternoon"
        },
        {
          "link": "https://247wallst.com/investing/etf/2026/07/21/mags-delivered-181-since-launch-but-equal-weighted-tech-concentration-is-now-a-liability/?.tsrc=rss",
          "published": "Tue, 21 Jul 2026 19:34:35 +0000",
          "source": "Yahoo Finance",
          "title": "MAGS Delivered 181% Since Launch, But Equal-Weighted Tech Concentration Is Now a Liability"
        }
      ],
      "AEM": [
        {
          "link": "https://finance.yahoo.com/markets/stocks/articles/heres-play-newmont-stock-q2-130100529.html?.tsrc=rss",
          "published": "Tue, 21 Jul 2026 13:01:00 +0000",
          "source": "Yahoo Finance",
          "title": "Here's How to Play Newmont Stock Before Q2 Earnings Release"
        },
        {
          "link": "https://www.mining-technology.com/news/grid-metals-avenir-jva-falcon-west-cesium/?.tsrc=rss",
          "published": "Tue, 21 Jul 2026 08:57:09 +0000",
          "source": "Yahoo Finance",
          "title": "Grid Metals, Avenir sign JVA for Falcon West Cesium in Manitoba"
        }
      ],
      "AENA.MC": [
        {
          "link": "https://finance.yahoo.com/news/aena-sme-sa-annsf-full-190111247.html?.tsrc=rss",
          "published": "Wed, 25 Feb 2026 19:01:11 +0000",
          "source": "Yahoo Finance",
          "title": "Aena SME SA (ANNSF) Full Year 2025 Earnings Call Highlights: Record Revenue and Passenger ..."
        },
        {
          "link": "https://finance.yahoo.com/news/top-european-dividend-stocks-consider-103149272.html?.tsrc=rss",
          "published": "Thu, 05 Feb 2026 10:31:49 +0000",
          "source": "Yahoo Finance",
          "title": "Top European Dividend Stocks To Consider In February 2026"
        }
      ],
      "AIR.PA": [
        {
          "link": "https://finance.yahoo.com/video/3m-turns-to-ai-to-fuel-turnaround-194739770.html?.tsrc=rss",
          "published": "Tue, 21 Jul 2026 19:47:39 +0000",
          "source": "Yahoo Finance",
          "title": "3M turns to AI to fuel turnaround"
        },
        {
          "link": "https://uk.finance.yahoo.com/news/rolls-royce-issues-burnham-ultimatum-193906545.html?.tsrc=rss",
          "published": "Tue, 21 Jul 2026 19:39:06 +0000",
          "source": "Yahoo Finance",
          "title": "Rolls-Royce issues Burnham with an ultimatum on \u00a33bn jet engine project"
        }
      ],
      "AMD": [
        {
          "link": "https://finance.yahoo.com/markets/stocks/articles/nvidia-isnt-leading-ai-stocks-190000877.html?.tsrc=rss",
          "published": "Tue, 21 Jul 2026 19:00:00 +0000",
          "source": "Yahoo Finance",
          "title": "NVIDIA Isn't Leading AI Stocks in 2026 - These 2 Are Up Over 180%"
        },
        {
          "link": "https://finance.yahoo.com/m/9c25c080-64c5-3e0c-8b74-ed7542cb1084/tsmc-is-raising-prices.-can.html?.tsrc=rss",
          "published": "Tue, 21 Jul 2026 18:27:00 +0000",
          "source": "Yahoo Finance",
          "title": "TSMC Is Raising Prices. Can Big Tech\u2019s AI Boom Afford the Bill?"
        }
      ],
      "BABA": [
        {
          "link": "https://finance.yahoo.com/markets/stocks/articles/alibabas-fintech-exposure-gets-boost-170249770.html?.tsrc=rss",
          "published": "Tue, 21 Jul 2026 17:02:49 +0000",
          "source": "Yahoo Finance",
          "title": "Alibaba's Fintech Exposure Gets New Boost"
        },
        {
          "link": "https://finance.yahoo.com/technology/ai/articles/alibaba-best-chinese-ai-play-163106852.html?.tsrc=rss",
          "published": "Tue, 21 Jul 2026 16:31:06 +0000",
          "source": "Yahoo Finance",
          "title": "Is Alibaba the Best Chinese AI Play After Apple\u2019s Endorsement?"
        }
      ],
      "BARC.L": [
        {
          "link": "https://finance.yahoo.com/markets/options/articles/barclays-broadly-syndicated-loans-live-123000325.html?.tsrc=rss",
          "published": "Tue, 21 Jul 2026 12:30:00 +0000",
          "source": "Yahoo Finance",
          "title": "Barclays' Broadly Syndicated Loans Go Live on Versana"
        },
        {
          "link": "https://finance.yahoo.com/energy/articles/fervo-energy-frvo-updates-sawtooth-081036409.html?.tsrc=rss",
          "published": "Tue, 21 Jul 2026 08:10:36 +0000",
          "source": "Yahoo Finance",
          "title": "Fervo Energy (FRVO) Updates Sawtooth 7 Progress, Is The Pullback Making It Cheap?"
        }
      ],
      "BP.L": [
        {
          "link": "https://finance.yahoo.com/energy/articles/sector-energy-171628910.html?.tsrc=rss",
          "published": "Tue, 21 Jul 2026 17:16:28 +0000",
          "source": "Yahoo Finance",
          "title": "Sector Update: Energy"
        },
        {
          "link": "https://finance.yahoo.com/energy/articles/adnoc-approves-6-2-billion-084900461.html?.tsrc=rss",
          "published": "Tue, 21 Jul 2026 08:49:00 +0000",
          "source": "Yahoo Finance",
          "title": "ADNOC Approves $6.2 Billion Gas Project in Abu Dhabi"
        }
      ],
      "CRCL": [
        {
          "link": "https://www.thestreet.com/crypto/markets/circle-robinhood-strategy-stocks-surge-on-bitcoin-comeback?.tsrc=rss",
          "published": "Tue, 21 Jul 2026 19:55:00 +0000",
          "source": "Yahoo Finance",
          "title": "Circle, Robinhood, Strategy stocks surge on Bitcoin comeback"
        },
        {
          "link": "https://finance.yahoo.com/m/75f0c47c-efd5-3d9c-94be-e0146d2ada7e/coinbase-stock-is-rallying..html?.tsrc=rss",
          "published": "Tue, 21 Jul 2026 18:21:00 +0000",
          "source": "Yahoo Finance",
          "title": "Coinbase Stock Is Rallying. Can Donald Trump\u2019s Ethics Compromise Save the Clarity Act?"
        }
      ],
      "DBK.DE": [
        {
          "link": "https://finance.yahoo.com/media-advertising/articles/amc-rolls-red-carpet-debt-145225000.html?.tsrc=rss",
          "published": "Tue, 21 Jul 2026 14:52:25 +0000",
          "source": "Yahoo Finance",
          "title": "AMC Rolls Out Red Carpet for Debt Investors to Trumpet Rebound"
        },
        {
          "link": "https://finance.yahoo.com/m/0cabe3af-5810-3d94-8cee-dbbc762a4ce0/deutsche-bank-supports.html?.tsrc=rss",
          "published": "Tue, 21 Jul 2026 14:00:00 +0000",
          "source": "Yahoo Finance",
          "title": "Deutsche Bank supports European Energy\u2019s Mokoan hybrid solar and battery project"
        }
      ],
      "EZJ.L": [
        {
          "link": "https://finance.yahoo.com/markets/options/articles/form-8-3-083000679.html?.tsrc=rss",
          "published": "Mon, 20 Jul 2026 08:30:00 +0000",
          "source": "Yahoo Finance",
          "title": "Form 8.3"
        },
        {
          "link": "https://moneyweek.com/investments/uk-stock-markets/can-andy-burnham-save-uk-stock-market?.tsrc=rss",
          "published": "Wed, 15 Jul 2026 16:13:32 +0000",
          "source": "Yahoo Finance",
          "title": "Can Andy Burnham save the UK\u2019s stock market?"
        }
      ],
      "GFS": [
        {
          "link": "https://finance.yahoo.com/technology/articles/wedbush-delivers-urgent-message-tsmc-184001343.html?.tsrc=rss",
          "published": "Tue, 14 Jul 2026 18:40:01 +0000",
          "source": "Yahoo Finance",
          "title": "Wedbush Delivers an Urgent Message for TSMC Stock Investors"
        },
        {
          "link": "https://finance.yahoo.com/markets/stocks/articles/globalfoundries-gfs-announces-production-readiness-132550167.html?.tsrc=rss",
          "published": "Sun, 12 Jul 2026 16:32:50 +0000",
          "source": "Yahoo Finance",
          "title": "GlobalFoundries (GFS) Announces Production Readiness of SLATE Wafer-to-Wafer Bonding Technology"
        }
      ],
      "IAG.L": [
        {
          "link": "https://finance.yahoo.com/markets/stocks/articles/boeing-airbus-delivery-delays-may-200528121.html?.tsrc=rss",
          "published": "Mon, 20 Jul 2026 20:05:28 +0000",
          "source": "Yahoo Finance",
          "title": "Boeing, Airbus Delivery Delays May Persist Another Five Years, BA Warns"
        },
        {
          "link": "https://www.proactiveinvestors.com/companies/news/1095311/ftse-100-live-global-stocks-fall-as-oil-prices-hit-three-week-high-on-iran-fighting-1095311.html?.tsrc=rss",
          "published": "Mon, 13 Jul 2026 06:19:00 +0000",
          "source": "Yahoo Finance",
          "title": "FTSE 100 Live: Stocks flat as Trump says US to be 'guardian of Hormuz strait'"
        }
      ],
      "ISP.MI": [
        {
          "link": "https://www.retailbankerinternational.com/news/monte-dei-paschi-intesa-offer-below-level/?.tsrc=rss",
          "published": "Fri, 17 Jul 2026 12:03:56 +0000",
          "source": "Yahoo Finance",
          "title": "Monte dei Paschi deem Intesa offer below average level"
        },
        {
          "link": "https://www.power-technology.com/news/financial-close-achieved-peoria-solar/?.tsrc=rss",
          "published": "Thu, 16 Jul 2026 11:09:14 +0000",
          "source": "Yahoo Finance",
          "title": "Financial close achieved on Sol Systems\u2019 123MWac Peoria Solar Project"
        }
      ],
      "LULU": [
        {
          "link": "https://stocktwits.com/news-articles/markets/equity/michael-burry-still-wont-buy-game-stop-ebay-strategy-but-calls-lulu-crash-a-no-brainer/cZZLMmmR7MH?.tsrc=rss",
          "published": "Mon, 20 Jul 2026 06:33:17 +0000",
          "source": "Yahoo Finance",
          "title": "Michael Burry Still Won't Buy GameStop's eBay Strategy \u2014 But Calls LULU Crash A 'No-Brainer'"
        },
        {
          "link": "https://finance.yahoo.com/markets/stocks/articles/lululemon-lulu-ascends-while-market-214502655.html?.tsrc=rss",
          "published": "Thu, 16 Jul 2026 21:45:02 +0000",
          "source": "Yahoo Finance",
          "title": "Lululemon (LULU) Ascends While Market Falls: Some Facts to Note"
        }
      ],
      "MKS.L": [
        {
          "link": "https://www.retail-insight-network.com/news/ms-opens-largest-ever-food-store/?.tsrc=rss",
          "published": "Fri, 17 Jul 2026 13:10:14 +0000",
          "source": "Yahoo Finance",
          "title": "M&S opens largest ever standalone food store in Godalming, UK"
        },
        {
          "link": "https://wwd.com/business-news/retail/marks-spencer-glam-new-interior-bespoke-offer-london-oxford-1239064459/?.tsrc=rss",
          "published": "Mon, 13 Jul 2026 19:52:38 +0000",
          "source": "Yahoo Finance",
          "title": "Marks & Spencer Goes Glam With New Interior Design, Bespoke Offer on Oxford Street in London"
        }
      ],
      "NDA-FI.HE": [
        {
          "link": "https://finance.yahoo.com/markets/stocks/articles/nordea-bank-abp-hlse-nda-060803087.html?.tsrc=rss",
          "published": "Sun, 19 Jul 2026 06:08:03 +0000",
          "source": "Yahoo Finance",
          "title": "Can Nordea Bank Abp (HLSE:NDA FI) Still Be Undervalued?"
        },
        {
          "link": "https://finance.yahoo.com/markets/stocks/articles/nordea-bank-abp-hlse-nda-050733459.html?.tsrc=rss",
          "published": "Sun, 19 Jul 2026 05:07:33 +0000",
          "source": "Yahoo Finance",
          "title": "Nordea Bank Abp (HLSE:NDA FI) Posted Fresh Earnings, Is The Stock Still Cheap?"
        }
      ],
      "NVDA": [
        {
          "link": "https://www.fool.com/investing/2026/07/21/why-msci-stock-is-plummeting-lower-today/?.tsrc=rss",
          "published": "Tue, 21 Jul 2026 20:05:53 +0000",
          "source": "Yahoo Finance",
          "title": "Why MSCI Stock Is Plummeting Lower Today"
        },
        {
          "link": "https://247wallst.com/investing/2026/07/21/beyond-gld-the-0-40-fee-drag-that-is-slowly-bleeding-your-gold-returns/?.tsrc=rss",
          "published": "Tue, 21 Jul 2026 19:47:28 +0000",
          "source": "Yahoo Finance",
          "title": "Beyond GLD: The 0.40% Fee Drag That Is Slowly Bleeding Your Gold Returns"
        }
      ],
      "NVTS": [
        {
          "link": "https://finance.yahoo.com/technology/ai/articles/ai-infrastructure-demand-accelerate-nvts-142400133.html?.tsrc=rss",
          "published": "Tue, 21 Jul 2026 14:24:00 +0000",
          "source": "Yahoo Finance",
          "title": "Can AI Infrastructure Demand Accelerate NVTS' Long-Term Growth?"
        },
        {
          "link": "https://www.fool.com/coverage/charts/2026/07/19/advanced-micro-devices-vs-navitas-semiconductor-here-s-what-the-quarterly-revenue-trends-of-these-artificial-intelligence-companies-reveal-to-investors/?.tsrc=rss",
          "published": "Sun, 19 Jul 2026 22:38:01 +0000",
          "source": "Yahoo Finance",
          "title": "Advanced Micro Devices vs. Navitas Semiconductor: Here's What The Quarterly Revenue Trends of These Artificial Intelligence Companies Reveal to Investors"
        }
      ],
      "NWG.L": [
        {
          "link": "https://finance.yahoo.com/economy/policy/articles/andy-burnham-set-become-uk-085510468.html?.tsrc=rss",
          "published": "Sat, 11 Jul 2026 08:55:10 +0000",
          "source": "Yahoo Finance",
          "title": "Andy Burnham set to become UK PM as policy agenda remains unclear"
        },
        {
          "link": "https://247wallst.com/investing/2026/07/10/5-solid-dividend-stocks-to-buy-in-july/?.tsrc=rss",
          "published": "Fri, 10 Jul 2026 14:49:18 +0000",
          "source": "Yahoo Finance",
          "title": "5 Solid Dividend Stocks to Buy in July"
        }
      ],
      "ORCL": [
        {
          "link": "https://finance.yahoo.com/video/oracle-stock-is-still-a-buy-analyst-outlines-his-bull-case-194817843.html?.tsrc=rss",
          "published": "Tue, 21 Jul 2026 19:48:17 +0000",
          "source": "Yahoo Finance",
          "title": "Oracle stock is still a buy: Analyst outlines his bull case"
        },
        {
          "link": "https://247wallst.com/investing/2026/07/21/we-must-act-now-16-nobel-laureates-issue-stark-warning-about-ai-job-threats/?.tsrc=rss",
          "published": "Tue, 21 Jul 2026 19:46:25 +0000",
          "source": "Yahoo Finance",
          "title": "\u201cWe Must Act Now\u201d: 16 Nobel Laureates Issue Stark Warning About AI Job Threats"
        }
      ],
      "PLTR": [
        {
          "link": "https://www.fool.com/investing/2026/07/21/palantir-stock-is-down-more-than-35-from-its-peak/?.tsrc=rss",
          "published": "Tue, 21 Jul 2026 17:20:00 +0000",
          "source": "Yahoo Finance",
          "title": "Palantir Stock Is Down More Than 35% from Its Peak. Is It Finally a Buy?"
        },
        {
          "link": "https://www.entrepreneur.com/business-news/billionaire-ceo-says-ai-could-make-him-20-times-richer?.tsrc=rss",
          "published": "Tue, 21 Jul 2026 15:10:22 +0000",
          "source": "Yahoo Finance",
          "title": "Billionaire CEO Says AI Could Make Him 20 Times Richer: \u2018That\u2019s a Problem for Society\u2019"
        }
      ],
      "RYA.IR": [
        {
          "link": "https://finance.yahoo.com/markets/stocks/articles/ryanair-q1-earnings-miss-lower-172600767.html?.tsrc=rss",
          "published": "Tue, 21 Jul 2026 17:26:00 +0000",
          "source": "Yahoo Finance",
          "title": "Ryanair Q1 Earnings Miss on Lower Fares and Fuel Cost Spike"
        },
        {
          "link": "https://finance.yahoo.com/markets/stocks/articles/company-news-july-21-2026-132700117.html?.tsrc=rss",
          "published": "Tue, 21 Jul 2026 13:27:00 +0000",
          "source": "Yahoo Finance",
          "title": "Company News for July 21, 2026"
        }
      ],
      "SGLN.L": [
        {
          "link": "https://uk.finance.yahoo.com/news/most-popular-stocks-funds-investors-uk-september-103611811.html?.tsrc=rss",
          "published": "Wed, 08 Oct 2025 10:36:11 +0000",
          "source": "Yahoo Finance",
          "title": "The most popular stocks and funds investors bought in September"
        },
        {
          "link": "https://uk.finance.yahoo.com/news/popular-stocks-funds-investors-bought-august-114043112.html?.tsrc=rss",
          "published": "Wed, 10 Sep 2025 11:40:43 +0000",
          "source": "Yahoo Finance",
          "title": "The most popular stocks and funds investors bought in August"
        }
      ],
      "SHEL.L": [
        {
          "link": "https://finance.yahoo.com/energy/articles/sector-energy-stocks-higher-tuesday-174434515.html?.tsrc=rss",
          "published": "Tue, 21 Jul 2026 17:44:34 +0000",
          "source": "Yahoo Finance",
          "title": "Sector Update: Energy Stocks Higher Tuesday Afternoon"
        },
        {
          "link": "https://finance.yahoo.com/energy/articles/sector-energy-171628910.html?.tsrc=rss",
          "published": "Tue, 21 Jul 2026 17:16:28 +0000",
          "source": "Yahoo Finance",
          "title": "Sector Update: Energy"
        }
      ],
      "SMCI": [
        {
          "link": "https://247wallst.com/investing/2026/07/21/super-micro-jumps-6-dell-climbs-7-hpe-rises-5-as-ai-hardware-rebounds-with-the-nasdaq/?.tsrc=rss",
          "published": "Tue, 21 Jul 2026 16:55:12 +0000",
          "source": "Yahoo Finance",
          "title": "Super Micro Jumps 6%, Dell Climbs 7%, HPE Rises 5% as AI Hardware Rebounds With the NASDAQ"
        },
        {
          "link": "https://finance.yahoo.com/markets/stocks/articles/1-cash-burning-stock-own-115826105.html?.tsrc=rss",
          "published": "Tue, 21 Jul 2026 11:58:26 +0000",
          "source": "Yahoo Finance",
          "title": "1 Cash-Burning Stock to Own for Decades and 2 Facing Challenges"
        }
      ],
      "STM": [
        {
          "link": "https://finance.yahoo.com/technology/ai/articles/ai-infrastructure-demand-accelerate-nvts-142400133.html?.tsrc=rss",
          "published": "Tue, 21 Jul 2026 14:24:00 +0000",
          "source": "Yahoo Finance",
          "title": "Can AI Infrastructure Demand Accelerate NVTS' Long-Term Growth?"
        },
        {
          "link": "https://finance.yahoo.com/markets/stocks/articles/stmicroelectronics-report-q2-earnings-buy-144100549.html?.tsrc=rss",
          "published": "Mon, 20 Jul 2026 14:41:00 +0000",
          "source": "Yahoo Finance",
          "title": "STMicroelectronics to Report Q2 Earnings: Buy Now or Wait for Results?"
        }
      ],
      "STMPA.PA": [
        {
          "link": "https://finance.yahoo.com/technology/ai/articles/ai-infrastructure-demand-accelerate-nvts-142400133.html?.tsrc=rss",
          "published": "Tue, 21 Jul 2026 14:24:00 +0000",
          "source": "Yahoo Finance",
          "title": "Can AI Infrastructure Demand Accelerate NVTS' Long-Term Growth?"
        },
        {
          "link": "https://finance.yahoo.com/markets/stocks/articles/stmicroelectronics-report-q2-earnings-buy-144100549.html?.tsrc=rss",
          "published": "Mon, 20 Jul 2026 14:41:00 +0000",
          "source": "Yahoo Finance",
          "title": "STMicroelectronics to Report Q2 Earnings: Buy Now or Wait for Results?"
        }
      ],
      "SWKS": [
        {
          "link": "https://finance.yahoo.com/markets/stocks/articles/skyworks-solutions-swks-expected-beat-140023215.html?.tsrc=rss",
          "published": "Tue, 21 Jul 2026 14:00:23 +0000",
          "source": "Yahoo Finance",
          "title": "Skyworks Solutions (SWKS) Expected to Beat Earnings Estimates: Can the Stock Move Higher?"
        },
        {
          "link": "https://finance.yahoo.com/technology/ai/articles/intel-amd-ai-earnings-setup-200050646.html?.tsrc=rss",
          "published": "Mon, 20 Jul 2026 20:00:50 +0000",
          "source": "Yahoo Finance",
          "title": "Intel and AMD Get AI Earnings Setup"
        }
      ],
      "TSLA": [
        {
          "link": "https://finance.yahoo.com/m/8d4cd9b9-0f40-37ee-98c0-2f2dc73336dc/what-construction-of-elon.html?.tsrc=rss",
          "published": "Tue, 21 Jul 2026 20:04:45 +0000",
          "source": "Yahoo Finance",
          "title": "What Construction Of Elon Musk's Terafab Would Mean For Tesla, SpaceX"
        },
        {
          "link": "https://247wallst.com/investing/etf/2026/07/21/mags-delivered-181-since-launch-but-equal-weighted-tech-concentration-is-now-a-liability/?.tsrc=rss",
          "published": "Tue, 21 Jul 2026 19:34:35 +0000",
          "source": "Yahoo Finance",
          "title": "MAGS Delivered 181% Since Launch, But Equal-Weighted Tech Concentration Is Now a Liability"
        }
      ],
      "TTE.PA": [
        {
          "link": "https://finance.yahoo.com/energy/articles/sector-energy-171628910.html?.tsrc=rss",
          "published": "Tue, 21 Jul 2026 17:16:28 +0000",
          "source": "Yahoo Finance",
          "title": "Sector Update: Energy"
        },
        {
          "link": "https://www.offshore-technology.com/news/adnoc-umm-shaif-gas-cap-development/?.tsrc=rss",
          "published": "Tue, 21 Jul 2026 13:45:27 +0000",
          "source": "Yahoo Finance",
          "title": "ADNOC approves $6.2bn Umm Shaif gas cap development"
        }
      ],
      "UBER": [
        {
          "link": "https://finance.yahoo.com/markets/stocks/articles/dominos-growth-trends-reflect-phase-161200755.html?.tsrc=rss",
          "published": "Tue, 21 Jul 2026 16:12:00 +0000",
          "source": "Yahoo Finance",
          "title": "Domino's Growth Trends Reflect a New Phase for Pizza Demand"
        },
        {
          "link": "https://finance.yahoo.com/markets/stocks/articles/dominos-business-outlook-turns-orders-155700668.html?.tsrc=rss",
          "published": "Tue, 21 Jul 2026 15:57:00 +0000",
          "source": "Yahoo Finance",
          "title": "Domino's Business Outlook Turns on Orders, Reach & Execution"
        }
      ],
      "UCG.MI": [
        {
          "link": "https://www.retailbankerinternational.com/news/unicredit-commerzbank-bid-talks/?.tsrc=rss",
          "published": "Mon, 20 Jul 2026 11:28:43 +0000",
          "source": "Yahoo Finance",
          "title": "Germany prepares terms for Commerzbank bid talks \u2013 report"
        },
        {
          "link": "https://www.electronicpaymentsinternational.com/news/ecb-picks-36-psps-for-digital-euro-pilot-due-to-start-next-year/?.tsrc=rss",
          "published": "Wed, 15 Jul 2026 06:47:16 +0000",
          "source": "Yahoo Finance",
          "title": "ECB picks 36 PSPs for digital euro pilot due to start next year"
        }
      ],
      "UNH": [
        {
          "link": "https://finance.yahoo.com/m/1d370289-2107-333c-931d-33a25620d1b7/dow-rises-500-points.-it%E2%80%99s.html?.tsrc=rss",
          "published": "Tue, 21 Jul 2026 17:19:10 +0000",
          "source": "Yahoo Finance",
          "title": "Dow Rises 500 Points. It\u2019s Not a Broad Rally."
        },
        {
          "link": "https://finance.yahoo.com/markets/stocks/articles/know-unitedhealth-unh-rating-upgrade-160002600.html?.tsrc=rss",
          "published": "Tue, 21 Jul 2026 16:00:02 +0000",
          "source": "Yahoo Finance",
          "title": "All You Need to Know About UnitedHealth (UNH) Rating Upgrade to Strong Buy"
        }
      ]
    },
    "source": "Yahoo Finance RSS"
  },
  "prediction": {
    "confidence": 75.45,
    "expected_market": "Late Cycle",
    "next_day_bias": "Neutral",
    "stance": "Neutral"
  },
  "reasoning": [
    "Score is a weighted blend of liquidity, credit, AI fundamentals, breadth, valuation, macro, and geopolitical proxies.",
    "Each subscore uses stable, explainable market-derived indicators so records remain comparable over time."
  ],
  "risk_regime": "Late Cycle",
  "stance": "Neutral",
  "sub_scores": {
    "ai_fundamentals": {
      "contributions": [],
      "evidence": [
        {
          "display": "-0.65%",
          "field": "return_20d",
          "label": "NVDA 20-day return",
          "symbol": "NVDA",
          "value": -0.6518097479552232
        },
        {
          "display": "-12.68%",
          "field": "return_20d",
          "label": "SMH 20-day return",
          "symbol": "SMH",
          "value": -12.681819590691024
        },
        {
          "display": "-15.62%",
          "field": "return_20d",
          "label": "SOXX 20-day return",
          "symbol": "SOXX",
          "value": -15.621136538050761
        },
        {
          "display": "False",
          "field": "above_50d",
          "label": "AVGO above 50-day",
          "symbol": "AVGO",
          "value": false
        }
      ],
      "reasoning": [
        "This checks whether the actual AI stock group is acting healthy.",
        "If NVDA, SMH, and SOXX are weak, the AI story may still be good but the trade is not confirming it."
      ],
      "score": 40.29
    },
    "credit": {
      "contributions": [],
      "evidence": [
        {
          "display": "-0.36%",
          "field": "return_20d",
          "label": "HYG 20-day return",
          "symbol": "HYG",
          "value": -0.3627720699831971
        },
        {
          "display": "-0.42%",
          "field": "return_20d",
          "label": "JNK 20-day return",
          "symbol": "JNK",
          "value": -0.4153696651494454
        },
        {
          "display": "False",
          "field": "above_50d",
          "label": "HYG above 50-day",
          "symbol": "HYG",
          "value": false
        },
        {
          "display": "False",
          "field": "above_50d",
          "label": "JNK above 50-day",
          "symbol": "JNK",
          "value": false
        }
      ],
      "reasoning": [
        "This asks: are investors still comfortable taking risk?",
        "If bond-market risk appetite is weak, be careful adding to volatile AI names."
      ],
      "score": 42.81
    },
    "geopolitical_risk": {
      "contributions": [
        {
          "label": "VIX fear",
          "points": 8,
          "value": 16.95,
          "why": "VIX shows whether fear is spreading into broad market pricing."
        },
        {
          "label": "Oil shock",
          "points": -9,
          "value": 7.25,
          "why": "A fast oil move can lift inflation fear and hurt growth-stock multiples."
        },
        {
          "label": "Gold bid",
          "points": 6,
          "value": 0.68,
          "why": "Gold rising quickly can mean investors are paying for safety."
        },
        {
          "label": "Dollar bid",
          "points": 6,
          "value": 0.23,
          "why": "A stronger dollar often tightens global financial conditions."
        },
        {
          "label": "QQQ shock",
          "points": -3,
          "value": -1.49,
          "why": "QQQ weakness shows the risk is hitting growth and mega-cap tech."
        },
        {
          "label": "Energy over AI",
          "points": -9,
          "value": 5.43,
          "why": "Energy outperforming chips can signal rotation away from AI toward oil shock beneficiaries."
        }
      ],
      "evidence": [
        {
          "display": "16.95",
          "field": "close",
          "label": "VIX level",
          "symbol": "^VIX",
          "value": 16.950001
        },
        {
          "display": "-0.47%",
          "field": "return_5d",
          "label": "SPY 5-day return",
          "symbol": "SPY",
          "value": -0.4721796043958726
        },
        {
          "display": "-1.49%",
          "field": "return_5d",
          "label": "QQQ 5-day return",
          "symbol": "QQQ",
          "value": -1.4895345176686337
        },
        {
          "display": "7.87%",
          "field": "return_5d",
          "label": "Brent oil 5-day return",
          "symbol": "BZ=F",
          "value": 7.872062744999564
        },
        {
          "display": "6.63%",
          "field": "return_5d",
          "label": "WTI oil 5-day return",
          "symbol": "CL=F",
          "value": 6.629697838653792
        },
        {
          "display": "0.68%",
          "field": "return_5d",
          "label": "Gold 5-day return",
          "symbol": "GC=F",
          "value": 0.6820799864953209
        },
        {
          "display": "0.23%",
          "field": "return_5d",
          "label": "Dollar 5-day return",
          "symbol": "DX-Y.NYB",
          "value": 0.23182286047507272
        },
        {
          "display": "-0.5%",
          "field": "return_5d",
          "label": "Long bond 5-day return",
          "symbol": "TLT",
          "value": -0.49952187203800014
        },
        {
          "display": "2.72%",
          "field": "return_5d",
          "label": "Energy stocks 5-day return",
          "symbol": "XLE",
          "value": 2.7216838854840386
        }
      ],
      "reasoning": [
        "This checks whether a shock is moving from headlines into oil, safe havens, volatility, and AI stocks.",
        "If oil, gold, dollar, and VIX rise together while QQQ/SMH weaken, reduce risk before the story gets priced in."
      ],
      "score": 71.12
    },
    "liquidity": {
      "contributions": [
        {
          "label": "VIX calm",
          "points": 8,
          "value": 16.95,
          "why": "Lower fear makes it easier for money to stay in AI and growth stocks."
        },
        {
          "label": "Dollar move",
          "points": -2,
          "value": 0.15,
          "why": "A stronger dollar can pull money away from risk assets."
        },
        {
          "label": "10Y yield level",
          "points": 2,
          "value": 4.63,
          "why": "Lower or stable yields are friendlier to growth stocks."
        },
        {
          "label": "10Y 20-day move",
          "points": 2,
          "value": 2.64,
          "why": "Falling yields usually give AI stocks more breathing room."
        },
        {
          "label": "SPY trend",
          "points": 8,
          "value": true,
          "why": "S&P 500 above its 50-day average means the broad market is still holding up."
        },
        {
          "label": "QQQ trend",
          "points": -12,
          "value": false,
          "why": "QQQ below its 50-day average warns that tech/growth may be losing support."
        },
        {
          "label": "HYG trend",
          "points": -8,
          "value": false,
          "why": "High-yield bonds below trend suggest investors are less comfortable taking risk."
        },
        {
          "label": "SMH trend",
          "points": -8,
          "value": false,
          "why": "Chip-stock trend matters because AI leadership depends heavily on semiconductors."
        }
      ],
      "evidence": [
        {
          "display": "16.95",
          "field": "close",
          "label": "VIX level",
          "symbol": "^VIX",
          "value": 16.950001
        },
        {
          "display": "0.15%",
          "field": "return_20d",
          "label": "Dollar 20-day return",
          "symbol": "DX-Y.NYB",
          "value": 0.1524519942323721
        },
        {
          "display": "4.63",
          "field": "close",
          "label": "10Y Treasury yield proxy",
          "symbol": "^TNX",
          "value": 4.628
        },
        {
          "display": "2.64%",
          "field": "return_20d",
          "label": "10Y yield 20-day change",
          "symbol": "^TNX",
          "value": 2.6391661122199928
        },
        {
          "display": "True",
          "field": "above_50d",
          "label": "SPY above 50-day",
          "symbol": "SPY",
          "value": true
        },
        {
          "display": "False",
          "field": "above_50d",
          "label": "QQQ above 50-day",
          "symbol": "QQQ",
          "value": false
        },
        {
          "display": "True",
          "field": "above_50d",
          "label": "Equal-weight S&P above 50-day",
          "symbol": "RSP",
          "value": true
        },
        {
          "display": "False",
          "field": "above_50d",
          "label": "HYG above 50-day",
          "symbol": "HYG",
          "value": false
        },
        {
          "display": "False",
          "field": "above_50d",
          "label": "SMH above 50-day",
          "symbol": "SMH",
          "value": false
        },
        {
          "display": "False",
          "field": "above_50d",
          "label": "SOXX above 50-day",
          "symbol": "SOXX",
          "value": false
        }
      ],
      "reasoning": [
        "This asks whether today's funding environment is friendly to AI and growth stocks.",
        "It combines fear, the dollar, rates, credit, broad-market trend, and chip-stock trend."
      ],
      "score": 54.6
    },
    "macro_risk": {
      "contributions": [],
      "evidence": [
        {
          "display": "4.63",
          "field": "close",
          "label": "10Y Treasury yield proxy",
          "symbol": "^TNX",
          "value": 4.628
        },
        {
          "display": "2.64%",
          "field": "return_20d",
          "label": "10Y yield 20-day change",
          "symbol": "^TNX",
          "value": 2.6391661122199928
        },
        {
          "display": "0.15%",
          "field": "return_20d",
          "label": "Dollar 20-day return",
          "symbol": "DX-Y.NYB",
          "value": 0.1524519942323721
        }
      ],
      "reasoning": [
        "Rates and the dollar can push growth stocks around.",
        "If rates rise fast, AI stocks can fall even when company news is still good."
      ],
      "score": 61.4
    },
    "market_breadth": {
      "contributions": [],
      "evidence": [
        {
          "display": "True",
          "field": "above_200d",
          "label": "SPY above 200-day",
          "symbol": "SPY",
          "value": true
        },
        {
          "display": "True",
          "field": "above_200d",
          "label": "QQQ above 200-day",
          "symbol": "QQQ",
          "value": true
        },
        {
          "display": "1.5%",
          "field": "return_20d",
          "label": "Equal-weight S&P 20-day return",
          "symbol": "RSP",
          "value": 1.502788027752544
        },
        {
          "display": "-0.55%",
          "field": "return_20d",
          "label": "Small-cap 20-day return",
          "symbol": "IWM",
          "value": -0.5499980007042327
        }
      ],
      "reasoning": [
        "This asks whether the rally is broad or just a few big names.",
        "A broad rally is safer. A narrow rally means AI leaders can get crowded fast."
      ],
      "score": 67.99
    },
    "valuation_risk": {
      "contributions": [],
      "evidence": [
        {
          "display": "7.28%",
          "field": "distance_from_200d",
          "label": "SPY distance from 200-day",
          "symbol": "SPY",
          "value": 7.284859105353814
        },
        {
          "display": "10.46%",
          "field": "distance_from_200d",
          "label": "QQQ distance from 200-day",
          "symbol": "QQQ",
          "value": 10.457560064747229
        },
        {
          "display": "32.1%",
          "field": "distance_from_200d",
          "label": "SMH distance from 200-day",
          "symbol": "SMH",
          "value": 32.104003374773725
        },
        {
          "display": "7.64%",
          "field": "distance_from_200d",
          "label": "NVDA distance from 200-day",
          "symbol": "NVDA",
          "value": 7.639078924332265
        }
      ],
      "reasoning": [
        "This checks whether prices have already run too far.",
        "If this weakens, new buys need more patience because the easy move may already be priced in."
      ],
      "score": 72.3
    }
  }
}
